{"stat.leaveGame":26,"stat.mineBlock.minecraft.cobblestone":35,"stat.swimOneCm":58028,"stat.useItem.minecraft.planks":1,"achievement.buildWorkBench":6,"stat.enderchestOpened":1,"stat.breakItem.minecraft.iron_pickaxe":3,"stat.useItem.minecraft.dirt":22,"achievement.exploreAllBiomes":{"value":0,"progress":["Beach","ForestHills","Stone Beach","Flower Forest","Forest","River","Ocean","Plains","Extreme Hills","Deep Ocean"]},"stat.craftItem.minecraft.furnace":10,"stat.entityKilledBy.Spider":1,"stat.useItem.minecraft.iron_ore":2,"stat.craftItem.minecraft.stone_pickaxe":1,"stat.flyOneCm":176798,"achievement.buildPickaxe":6,"achievement.buildBetterPickaxe":4,"stat.mineBlock.minecraft.iron_ore":38,"stat.timeSinceDeath":175,"stat.useItem.minecraft.iron_pickaxe":833,"stat.craftItem.minecraft.wooden_pickaxe":2,"stat.furnaceInteraction":21,"stat.mineBlock.minecraft.coal_ore":61,"stat.entityKilledBy.Skeleton":4,"achievement.buildSword":1,"achievement.mineWood":104,"stat.sprintOneCm":147223,"stat.craftItem.minecraft.stick":84,"stat.craftItem.minecraft.wooden_axe":1,"achievement.openInventory":140,"stat.mineBlock.minecraft.crafting_table":2,"stat.useItem.minecraft.wooden_shovel":31,"stat.entityKilledBy.Creeper":1,"stat.useItem.minecraft.beef":2,"achievement.buildFurnace":10,"stat.deaths":23,"stat.drop":8,"stat.playOneMinute":191115,"stat.craftItem.minecraft.wooden_shovel":1,"stat.useItem.minecraft.wooden_sword":7,"stat.killEntity.Sheep":1,"stat.craftItem.minecraft.iron_pickaxe":3,"stat.mineBlock.minecraft.tallgrass":14,"stat.diveOneCm":60548,"stat.chestOpened":6,"stat.useItem.minecraft.stone":3,"stat.useItem.minecraft.chicken":7,"stat.jump":2968,"stat.fallOneCm":83618,"stat.crouchOneCm":2079,"stat.craftItem.minecraft.iron_ingot":20,"stat.craftItem.minecraft.torch":40,"stat.craftItem.minecraft.chest":2,"stat.useItem.minecraft.cooked_chicken":3,"stat.craftingTableInteraction":29,"stat.useItem.minecraft.sapling":1,"stat.damageTaken":5831,"stat.useItem.minecraft.wooden_pickaxe":56,"stat.useItem.minecraft.furnace":10,"stat.craftItem.minecraft.wooden_sword":1,"stat.entityKilledBy.Zombie":2,"stat.mineBlock.minecraft.gravel":13,"stat.useItem.minecraft.stone_pickaxe":132,"stat.damageDealt":2055,"stat.killEntity.Rabbit":2,"stat.mineBlock.minecraft.ender_chest":1,"stat.mineBlock.minecraft.dirt":58,"stat.useItem.minecraft.crafting_table":6,"stat.walkOneCm":739319,"stat.useItem.minecraft.torch":26,"stat.animalsBred":1,"stat.playerKills":3,"stat.useItem.minecraft.chest":2,"stat.useItem.minecraft.log":1,"stat.useItem.minecraft.cobblestone":185,"stat.craftItem.minecraft.crafting_table":6,"stat.breakItem.minecraft.stone_pickaxe":1,"stat.craftItem.minecraft.iron_chestplate":1,"stat.killEntity.Skeleton":1,"stat.craftItem.minecraft.planks":280,"stat.killEntity.Chicken":12,"stat.mobKills":16,"stat.mineBlock.minecraft.log":114,"stat.craftItem.minecraft.wooden_door":3,"stat.craftItem.minecraft.cooked_chicken":3,"stat.useItem.minecraft.wooden_door":3,"achievement.acquireIron":5,"stat.mineBlock.minecraft.leaves":5,"stat.useItem.minecraft.wooden_axe":17,"stat.mineBlock.minecraft.stone":830}