{"stat.chestOpened":20,"stat.useItem.minecraft.stone":7,"stat.useItem.minecraft.iron_axe":35,"stat.mineBlock.minecraft.dispenser":1,"stat.leaveGame":8,"stat.mineBlock.minecraft.cobblestone":1,"stat.mineBlock.minecraft.anvil":1,"stat.craftItem.minecraft.iron_axe":1,"stat.swimOneCm":24192,"stat.jump":1094,"stat.useItem.minecraft.sand":1,"stat.fallOneCm":28801,"stat.useItem.minecraft.planks":3,"stat.climbOneCm":2240,"stat.crouchOneCm":8238,"stat.mineBlock.minecraft.chest":4,"stat.craftItem.minecraft.iron_ingot":19,"stat.useItem.minecraft.dirt":17,"achievement.exploreAllBiomes":{"value":0,"progress":["Beach","ForestHills","Stone Beach","Forest","River","Ocean","Plains","Extreme Hills"]},"stat.useItem.minecraft.water_bucket":3,"stat.craftingTableInteraction":5,"stat.craftItem.minecraft.furnace":4,"stat.useItem.minecraft.golden_sword":24,"stat.craftItem.minecraft.iron_boots":1,"stat.damageTaken":2292,"stat.mineBlock.minecraft.furnace":10,"stat.mineBlock.minecraft.red_flower":1,"stat.useItem.minecraft.furnace":3,"stat.dispenserInspected":3,"stat.flyOneCm":51862,"stat.craftItem.minecraft.iron_shovel":1,"stat.mineBlock.minecraft.sand":12,"stat.useItem.minecraft.stone_sword":12,"stat.damageDealt":2915,"stat.mineBlock.minecraft.iron_ore":23,"stat.timeSinceDeath":9436,"stat.mineBlock.minecraft.dirt":12,"stat.useItem.minecraft.iron_pickaxe":95,"stat.useItem.minecraft.crafting_table":1,"stat.walkOneCm":318315,"stat.playerKills":4,"stat.useItem.minecraft.chest":1,"stat.breakItem.minecraft.golden_sword":1,"stat.useItem.minecraft.log":1,"stat.useItem.minecraft.cobblestone":4,"stat.furnaceInteraction":8,"stat.useItem.minecraft.cooked_porkchop":1,"stat.mineBlock.minecraft.coal_ore":10,"stat.killEntity.Creeper":1,"stat.entityKilledBy.Skeleton":1,"achievement.mineWood":6,"stat.sprintOneCm":73831,"stat.craftItem.minecraft.stick":44,"stat.killEntity.Skeleton":3,"achievement.openInventory":38,"stat.craftItem.minecraft.planks":36,"stat.mineBlock.minecraft.crafting_table":1,"stat.useItem.minecraft.diamond_pickaxe":4,"stat.mobKills":5,"stat.useItem.minecraft.bucket":2,"stat.entityKilledBy.Creeper":1,"stat.deaths":8,"stat.mineBlock.minecraft.planks":3,"stat.breakItem.minecraft.iron_axe":1,"stat.drop":4,"stat.mineBlock.minecraft.leaves":2,"stat.playOneMinute":69690,"stat.craftItem.minecraft.iron_pickaxe":2,"stat.killEntity.Zombie":1,"stat.mineBlock.minecraft.stone":49,"stat.mineBlock.minecraft.tallgrass":3,"stat.diveOneCm":28619}