{"stat.killEntity.Skeleton":1,"stat.killEntity.Bat":1,"stat.craftItem.minecraft.furnace":1,"stat.walkOneCm":74530,"achievement.openInventory":4,"stat.craftItem.minecraft.planks":16,"stat.leaveGame":1,"stat.mineBlock.minecraft.crafting_table":2,"stat.damageTaken":70,"stat.craftItem.minecraft.crafting_table":1,"stat.furnaceInteraction":3,"stat.craftItem.minecraft.stone_pickaxe":1,"stat.useItem.minecraft.wooden_pickaxe":15,"stat.useItem.minecraft.furnace":1,"stat.mobKills":2,"stat.mineBlock.minecraft.coal_ore":33,"stat.mineBlock.minecraft.log":4,"achievement.buildFurnace":1,"stat.flyOneCm":300,"stat.drop":2,"stat.jump":126,"stat.mineBlock.minecraft.leaves":1,"achievement.buildPickaxe":2,"stat.swimOneCm":4984,"stat.playOneMinute":17946,"stat.fallOneCm":902,"stat.useItem.minecraft.stone_pickaxe":120,"achievement.buildWorkBench":1,"stat.damageDealt":280,"achievement.buildBetterPickaxe":1,"stat.mineBlock.minecraft.iron_ore":55,"stat.timeSinceDeath":17946,"achievement.mineWood":1,"stat.useItem.minecraft.wooden_axe":10,"stat.useItem.minecraft.dirt":1,"stat.mineBlock.minecraft.dirt":1,"stat.useItem.minecraft.crafting_table":3,"stat.sprintOneCm":169,"stat.craftItem.minecraft.wooden_pickaxe":1,"stat.mineBlock.minecraft.stone":45,"achievement.exploreAllBiomes":{"value":0,"progress":["Savanna Plateau","River","Savanna"]},"stat.diveOneCm":1384,"stat.craftItem.minecraft.stick":8,"stat.craftItem.minecraft.wooden_axe":1,"stat.mineBlock.minecraft.red_mushroom":3,"stat.craftingTableInteraction":5}