{"stat.chestOpened":2,"stat.leaveGame":16,"stat.mineBlock.minecraft.cobblestone":2,"stat.useItem.minecraft.diamond_sword":2,"stat.useItem.minecraft.mutton":2,"stat.jump":1249,"stat.swimOneCm":51613,"stat.fallOneCm":28024,"stat.useItem.minecraft.rabbit":2,"stat.useItem.minecraft.dirt":7,"achievement.exploreAllBiomes":{"value":0,"progress":["ForestHills","Birch Forest","Plains","Beach","DesertHills","Stone Beach","Extreme Hills+","Ice Plains","Forest","River","Ocean","Desert","Ice Mountains","Savanna","Deep Ocean"]},"stat.craftingTableInteraction":8,"stat.damageTaken":1321,"stat.mineBlock.minecraft.torch":2,"stat.flyOneCm":18509,"stat.entityKilledBy.Zombie":1,"stat.useItem.minecraft.stone_pickaxe":86,"stat.damageDealt":475,"stat.killEntity.Rabbit":1,"stat.useItem.minecraft.wool":1,"stat.mineBlock.minecraft.iron_ore":4,"stat.timeSinceDeath":64488,"stat.mineBlock.minecraft.dirt":13,"stat.useItem.minecraft.crafting_table":1,"stat.walkOneCm":291316,"stat.useItem.minecraft.torch":2,"stat.useItem.minecraft.potato":1,"stat.useItem.minecraft.cobblestone":6,"stat.useItem.minecraft.golden_carrot":3,"stat.mineBlock.minecraft.coal_ore":24,"stat.entityKilledBy.Skeleton":1,"achievement.mineWood":14,"stat.sprintOneCm":5475,"stat.craftItem.minecraft.stick":16,"stat.useItem.minecraft.bed":6,"achievement.openInventory":36,"stat.craftItem.minecraft.planks":40,"stat.mineBlock.minecraft.crafting_table":1,"stat.mobKills":2,"stat.mineBlock.minecraft.log":14,"stat.craftItem.minecraft.wooden_door":3,"stat.useItem.minecraft.wooden_door":1,"stat.deaths":4,"stat.drop":1,"stat.mineBlock.minecraft.leaves":1,"stat.playOneMinute":134464,"stat.killEntity.Sheep":1,"stat.mineBlock.minecraft.stone":52,"stat.mineBlock.minecraft.tallgrass":4,"stat.diveOneCm":32260}